{
  "selected_hook": "売ろうと思ってから、もうどのくらい経つだろう。",
  "addressed_anxiety": "「売ると決めていないのに相談していいのか」「付属品が揃っているかどうか不安」「査定に行ったら断りにくくなりそう」という複合的な行動抑制を、映像の丁寧な査定プロセスと低ハードルCTAで静かに解消する",
  "content_category": "査定ポイント型",
  "narrative_formula_type": "anxiety_shift_reassure_cta",
  "recommended_duration_range": {
    "min_sec": 50,
    "max_sec": 65
  },
  "sections": [
    {
      "section_id": 1,
      "section_name": "フック（回想型・感情停滞の代弁）",
      "goal": "「売ろうと思ってから動けていない」という視聴者の内的状態を静かに言語化し、手を止めさせる",
      "start_hint": "0秒",
      "end_hint": "4〜5秒",
      "narration_summary": "「売ろうと思ってから、もうどのくらい経つだろう。」という独り言に近い問いかけで、長期先延ばしの感覚を代弁する",
      "visual_evidence_required": [
        "エルメスのロゴが入ったオレンジ色の箱（開梱前の状態）"
      ],
      "candidate_clips": [
        {
          "source_file": "IMG_9267.mov",
          "timecode": "00:01",
          "description": "エルメスのロゴが入ったオレンジ色の箱のアップ"
        }
      ],
      "cta_role": false,
      "estimated_duration_sec": 5
    },
    {
      "section_id": 2,
      "section_name": "ペイン（行動できていない本音に寄り添う）",
      "goal": "「売ると決めていないのに相談していいのか」という気まずさ・迷いを代弁し、視聴者に「そうそう」と感じさせる",
      "start_hint": "5秒",
      "end_hint": "12〜13秒",
      "narration_summary": "「箱も付属品もちゃんとあるのに、なんとなく踏み出せないまま。」というトーンで、行動を止めている本音をそっと言語化する",
      "visual_evidence_required": [
        "オリジナルボックスから保存袋を取り出す様子",
        "保存袋のクローズアップ"
      ],
      "candidate_clips": [
        {
          "source_file": "IMG_9258.mov",
          "timecode": "00:29",
          "description": "保存袋の露出シーン"
        },
        {
          "source_file": "IMG_9258.mov",
          "timecode": "00:33",
          "description": "保存袋のロゴのクローズアップ"
        }
      ],
      "cta_role": false,
      "estimated_duration_sec": 8
    },
    {
      "section_id": 3,
      "section_name": "シフト（思い込みをひっそり崩す）",
      "goal": "「査定＝売ると決めること」という思い込みを、断定せずに静かに解きほぐす",
      "start_hint": "13秒",
      "end_hint": "22〜23秒",
      "narration_summary": "「査定は、売る宣言じゃなくていいんです。今の相場を知るだけでも、全然かまわない。」というトーンで、行動の敷居を下げる",
      "visual_evidence_required": [
        "バッグを保存袋から取り出す様子",
        "バッグ正面・背面の全体確認映像"
      ],
      "candidate_clips": [
        {
          "source_file": "IMG_9258.mov",
          "timecode": "01:03",
          "description": "保存袋からバッグを取り出すシーン"
        },
        {
          "source_file": "IMG_9267.mov",
          "timecode": "00:04",
          "description": "箱から黒いバッグを取り出すシーン"
        }
      ],
      "cta_role": false,
      "estimated_duration_sec": 10
    },
    {
      "section_id": 4,
      "section_name": "プルーフ（映像の事実を丁寧に提示）",
      "goal": "正面・底面・金具・内側刻印など複数アングルを見せながら「丁寧に見ている」姿勢を伝える。フルセットの付属品も映す",
      "start_hint": "23秒",
      "end_hint": "42〜44秒",
      "narration_summary": "「革の表情、底鋲、金具、内側のスタンプ。ひとつひとつ、丁寧に見ていきます。ロックも鍵も、箱も保存袋も。付属品の状態も含めて確認します。」というナレーションで、査定プロセスの誠実さを映像と連動させる",
      "visual_evidence_required": [
        "バッグ正面・背面・側面の映像",
        "底面と底鋲のクローズアップ",
        "革の質感・ステッチのクローズアップ",
        "内側の「HERMES MADE IN FRANCE」スタンプ",
        "ロックと鍵の露出シーン",
        "バックル・金具のクローズアップ"
      ],
      "candidate_clips": [
        {
          "source_file": "IMG_9267.mov",
          "timecode": "00:09",
          "description": "バッグ前面・背面、シボ革の質感とバックルが見える"
        },
        {
          "source_file": "IMG_9258.mov",
          "timecode": "01:22",
          "description": "バッグの底面と底鋲のクローズアップ"
        },
        {
          "source_file": "IMG_9258.mov",
          "timecode": "01:35",
          "description": "バッグの側面とステッチのクローズアップ"
        },
        {
          "source_file": "IMG_9258.mov",
          "timecode": "01:50",
          "description": "内側の「HERMES MADE IN FRANCE」スタンプ"
        },
        {
          "source_file": "IMG_9258.mov",
          "timecode": "02:40",
          "description": "ロックと鍵の露出シーン"
        },
        {
          "source_file": "IMG_9267.mov",
          "timecode": "00:18",
          "description": "バックルのクローズアップ"
        }
      ],
      "cta_role": false,
      "estimated_duration_sec": 20
    },
    {
      "section_id": 5,
      "section_name": "ベネフィットブリッジ（判断整理・何が決められるかを言い切る）",
      "goal": "「査定後に何が自分で決められるようになるか」を伝え、問い合わせへの動機を自然に高める",
      "start_hint": "44秒",
      "end_hint": "50〜52秒",
      "narration_summary": "「今の相場感が分かると、売るかどうか、自分のペースで決められます。」というトーンで、自律的な判断を主語にした benefit を伝える",
      "visual_evidence_required": [
        "バッグ全体の正面映像（状態良好・フルセットを印象づける）"
      ],
      "candidate_clips": [
        {
          "source_file": "IMG_9267.mov",
          "timecode": "00:09",
          "description": "バッグ前面・背面の全体確認映像"
        }
      ],
      "cta_role": false,
      "estimated_duration_sec": 7
    },
    {
      "section_id": 6,
      "section_name": "安心感（今すぐ売らなくていい・決めなくていい）",
      "goal": "「問い合わせたら売ることになる」という圧迫感を取り除き、最後の一歩を踏み出しやすくする",
      "start_hint": "51〜52秒",
      "end_hint": "57〜58秒",
      "narration_summary": "「査定した後で、やっぱりやめる、という判断ももちろんできます。」という一言で、プレッシャーゼロの姿勢を静かに伝える",
      "visual_evidence_required": [
        "オリジナルボックス・保存袋など付属品一式が見える俯瞰映像"
      ],
      "candidate_clips": [
        {
          "source_file": "IMG_9258.mov",
          "timecode": "00:00",
          "description": "開梱開始・付属品一式が揃った俯瞰シーン"
        }
      ],
      "cta_role": false,
      "estimated_duration_sec": 6
    },
    {
      "section_id": 7,
      "section_name": "低ハードルCTA（写真3枚でOK・相場だけでもOK）",
      "goal": "LINEへの問い合わせへのハードルを最小化し、視聴者に「それならできる」と感じさせる",
      "start_hint": "57〜58秒",
      "end_hint": "63〜65秒",
      "narration_summary": "「写真3枚をLINEで送るだけで、まず相場感だけ聞けます。エルメス専門買取TBT、プロフィールのリンクからどうぞ。」というトーンで、最短行動を提示する",
      "visual_evidence_required": [
        "HERMÈSロゴのクローズアップ（信頼感の補強）"
      ],
      "candidate_clips": [
        {
          "source_file": "IMG_9267.mov",
          "timecode": "00:01",
          "description": "エルメスのロゴが入ったオレンジ色の箱のアップ"
        }
      ],
      "cta_role": true,
      "estimated_duration_sec": 7
    }
  ],
  "differentiation_note": "「箱・付属品が揃っているのに動けていない」という層に対し、TBTは「写真3枚で相場だけ聞くところから始めていい」という導線を提示できる。フルセット状態という映像事実を証拠にしながら、数字訴求ではなく『自分で判断できる状態になる』という文脈で差別化する。",
  "forbidden_claim_check": [],
  "caption": "箱も、保存袋も、鍵も、ロックも。\nちゃんと揃っていたのに、ずっとクローゼットの中でした。\n\n売ると決めていないのに相談してもいいのか、と思うと\nなかなか一歩が踏み出せなくて。\n\nでも、査定って「売る宣言」じゃないんです。\n今の相場を知るだけでも、全然いい。\n\n写真3枚をLINEで送るだけで、まず相場感だけ教えてもらえます。\n決めるのは、そのあとで。\n\nずっと気になっていたなら、それだけ試してみませんか。\n\nエルメス専門買取 TBT（東京・蔵前）",
  "emotional_design": {
    "target_inner_conflict": "箱も付属品も揃っているのに、「売ると決めていないのに連絡していいのか」という迷いで、ずっと動けていない。",
    "hidden_fear": "査定に行ったら売ることを急かされたり、断りにくい雰囲気になったりしたくない",
    "embarrassment_trigger": "売るかどうかまだ決めていないのに問い合わせるのは失礼かもしれない、という気まずさ",
    "belief_to_shift": "査定に相談するのは、売ると決めてからするもののはず",
    "shift_statement": "査定は「売る宣言」ではなく、今の相場を自分の目で確認するための入口でもあるかもしれません",
    "emotional_hook_type": "回想型",
    "reassurance_angle": "売ると決めていなくても大丈夫。相場を知るだけでも、立派な一歩です。",
    "cta_barrier_reduction": "知識がなくても大丈夫 / 写真3枚をLINEで送るだけでOK / 査定後に売らなくてもOK",
    "benefit_design": {
      "primary_benefit": "自分のピコタンが今どのくらいの相場なのかが分かり、売るかどうかを自分のペースで決められる",
      "benefit_angle": "判断整理",
      "why_now": "箱・保存袋・ロック・鍵がすべて揃ったフルセット状態であり、状態も良好なうちに相場感を把握しておくと、売るかどうかの判断軸が持ちやすくなります",
      "decision_value": "「今売るべきか、持ち続けるか」を自分で決められる"
    }
  }
}